blackspammerbd_weblab/__init__.py
blackspammerbd_weblab/admin_bypass.py
blackspammerbd_weblab/admin_finder.py
blackspammerbd_weblab/brute_force.py
blackspammerbd_weblab/check_sql.py
blackspammerbd_weblab/link_extractor.py
blackspammerbd_weblab/utils.py
blackspammerbd_weblab-0.0.0.dist-info/licenses/LICENSE
blackspammerbd_weblab-0.0.0.dist-info/METADATA
blackspammerbd_weblab-0.0.0.dist-info/WHEEL
blackspammerbd_weblab-0.0.0.dist-info/entry_points.txt
blackspammerbd_weblab-0.0.0.dist-info/top_level.txt
blackspammerbd_weblab-0.0.0.dist-info/RECORD
