Metadata-Version: 2.4
Name: blackspammerbd-weblab
Version: 0.0.0
Summary: Most Powerful & Professional Web Security Tool - 2025 by BLACK SPAMMER BD
Home-page: https://github.com/BlackSpammerBd/blackspammerbd-weblab
Author: BLACK SPAMMER BD
Author-email: shawponsp6@gmail.com
Classifier: Programming Language :: Python :: 3
Classifier: Operating System :: OS Independent
Requires-Python: >=3.7
License-File: LICENSE
Requires-Dist: requests>=2.25
Requires-Dist: beautifulsoup4>=4.9
Requires-Dist: termcolor>=1.1
Requires-Dist: urllib3>=1.26
Requires-Dist: colorama>=0.4
Requires-Dist: tqdm>=4.60
Requires-Dist: lxml>=4.6
Dynamic: author
Dynamic: author-email
Dynamic: classifier
Dynamic: home-page
Dynamic: license-file
Dynamic: requires-dist
Dynamic: requires-python
Dynamic: summary
